{
  "id": "tw12139732",
  "url": "https://asia.pokemon-card.com/tw/users/tw12139732/?eventFilter=4&eventGivingCSPPointsFlg=1",
  "fetchedAt": "2026-04-11T03:00:09.340Z",
  "totalEvents": 16,
  "participatedTournaments": [
    {
      "pageNo": 1,
      "rowIndex": 16,
      "activityName": "2025-26 臺灣高級球聯盟賽 賽季2-4 (大師組)-二次抽選",
      "eventTime": "02-27-2026 08:30",
      "eventDateTime": "2026-02-27 08:30",
      "location": "Saka Saka Limited Taiwan Branch",
      "address": "台北市中山區林森北路372號6樓之一",
      "rank": "-",
      "lp": "-"
    },
    {
      "pageNo": 1,
      "rowIndex": 15,
      "activityName": "2025-26 Taiwan Great Ball League Season 2",
      "eventTime": "01-04-2026 14:00",
      "eventDateTime": "2026-01-04 14:00",
      "location": "幽靈屋",
      "address": "台北市南港區忠孝東路七段625巷33號",
      "rank": "-",
      "lp": "-"
    },
    {
      "pageNo": 1,
      "rowIndex": 14,
      "activityName": "2025-26 Taiwan Great Ball League Season 2",
      "eventTime": "01-04-2026 12:00",
      "eventDateTime": "2026-01-04 12:00",
      "location": "兔妞桌遊",
      "address": "桃園市蘆竹區忠孝西路180號2樓",
      "rank": "-",
      "lp": "-"
    },
    {
      "pageNo": 1,
      "rowIndex": 13,
      "activityName": "2025-26 Taiwan Great Ball League Season 2",
      "eventTime": "12-28-2025 14:00",
      "eventDateTime": "2025-12-28 14:00",
      "location": "貓腳印 桃園店",
      "address": "桃園市桃園區中華路1號11樓",
      "rank": "-",
      "lp": "-"
    },
    {
      "pageNo": 1,
      "rowIndex": 12,
      "activityName": "2025-26 Taiwan Great Ball League Season 2",
      "eventTime": "12-14-2025 10:00",
      "eventDateTime": "2025-12-14 10:00",
      "location": "一刻館卡片遊戲專賣店",
      "address": "桃園市桃園區中華路43號2樓",
      "rank": "-",
      "lp": "-"
    },
    {
      "pageNo": 1,
      "rowIndex": 11,
      "activityName": "2025-26 Taiwan Great Ball League Season 1",
      "eventTime": "11-09-2025 14:00",
      "eventDateTime": "2025-11-09 14:00",
      "location": "貓腳印 桃園店",
      "address": "桃園市桃園區中華路1號11樓",
      "rank": "21",
      "lp": "4"
    },
    {
      "pageNo": 1,
      "rowIndex": 2,
      "activityName": "2025-26 Taiwan Premier Ball League TCG Division Masters Category",
      "eventTime": "11-01-2025 09:00",
      "eventDateTime": "2025-11-01 09:00",
      "location": "The Pokémon Company",
      "address": "Roppongi Hills Mori Tower 8F, 6-10-1 Roppongi, Minato-ku, Tokyo, Japan",
      "rank": "852",
      "lp": "-"
    },
    {
      "pageNo": 1,
      "rowIndex": 10,
      "activityName": "2025-26 Taiwan Great Ball League Season 1",
      "eventTime": "10-26-2025 14:00",
      "eventDateTime": "2025-10-26 14:00",
      "location": "奇幻桌遊複合式餐廳",
      "address": "新北市土城區裕生路21巷6弄37號B1之7(A15)",
      "rank": "-",
      "lp": "-"
    },
    {
      "pageNo": 1,
      "rowIndex": 9,
      "activityName": "2025-26 Taiwan Great Ball League Season 1",
      "eventTime": "10-26-2025 12:00",
      "eventDateTime": "2025-10-26 12:00",
      "location": "兔妞桌遊",
      "address": "桃園市蘆竹區忠孝西路180號2樓",
      "rank": "-",
      "lp": "-"
    },
    {
      "pageNo": 1,
      "rowIndex": 8,
      "activityName": "2025-26 Taiwan Great Ball League Season 1",
      "eventTime": "10-24-2025 11:00",
      "eventDateTime": "2025-10-24 11:00",
      "location": "一刻館卡片遊戲專賣店",
      "address": "桃園市桃園區中華路43號2樓",
      "rank": "-",
      "lp": "-"
    },
    {
      "pageNo": 1,
      "rowIndex": 7,
      "activityName": "2025-26 臺灣高級球聯盟賽 賽季1-2",
      "eventTime": "10-05-2025 08:00",
      "eventDateTime": "2025-10-05 08:00",
      "location": "Saka Saka Limited Taiwan Branch",
      "address": "台北市中山區林森北路372號6樓之一",
      "rank": "-",
      "lp": "-"
    },
    {
      "pageNo": 1,
      "rowIndex": 6,
      "activityName": "2025-26 Taiwan Great Ball League Season 1",
      "eventTime": "10-04-2025 10:00",
      "eventDateTime": "2025-10-04 10:00",
      "location": "南瓜鎮",
      "address": "新北市三峽區國光街91號",
      "rank": "-",
      "lp": "-"
    },
    {
      "pageNo": 1,
      "rowIndex": 5,
      "activityName": "2025-26 Taiwan Great Ball League Season 1",
      "eventTime": "09-29-2025 13:00",
      "eventDateTime": "2025-09-29 13:00",
      "location": "元氣滿屋",
      "address": "新北市板橋區漢生西路145號1樓",
      "rank": "-",
      "lp": "-"
    },
    {
      "pageNo": 1,
      "rowIndex": 4,
      "activityName": "2025-26 Taiwan Great Ball League Season 1",
      "eventTime": "09-21-2025 14:00",
      "eventDateTime": "2025-09-21 14:00",
      "location": "貓腳印 桃園店",
      "address": "桃園市桃園區中華路1號11樓",
      "rank": "-",
      "lp": "-"
    },
    {
      "pageNo": 1,
      "rowIndex": 3,
      "activityName": "2025-26 Taiwan Great Ball League Season 1",
      "eventTime": "09-07-2025 10:00",
      "eventDateTime": "2025-09-07 10:00",
      "location": "一刻館卡片遊戲專賣店",
      "address": "桃園市桃園區中華路43號2樓",
      "rank": "-",
      "lp": "-"
    },
    {
      "pageNo": 1,
      "rowIndex": 1,
      "activityName": "Premier Ball League 2024-25 Taiwan TCG Division Masters Category",
      "eventTime": "11-30-2024 00:30",
      "eventDateTime": "2024-11-30 00:30",
      "location": "The Pokémon Company",
      "address": "Roppongi Hills Mori Tower 8F, 6-10-1 Roppongi, Minato-ku, Tokyo, Japan",
      "rank": "599",
      "lp": "-"
    }
  ]
}
