{
  "id": "tw16237500",
  "url": "https://asia.pokemon-card.com/tw/users/tw16237500/?eventFilter=4&eventGivingCSPPointsFlg=1",
  "fetchedAt": "2026-04-25T00:45:25.761Z",
  "totalEvents": 2,
  "participatedTournaments": [
    {
      "pageNo": 1,
      "rowIndex": 2,
      "activityName": "2025-26 Taiwan Great Ball League Season 2",
      "eventTime": "12-06-2025 13:30",
      "eventDateTime": "2025-12-06 13:30",
      "location": "SAGA TCG店",
      "address": "宜蘭縣宜蘭市復興路一段8號1樓",
      "rank": "24",
      "lp": "-"
    },
    {
      "pageNo": 1,
      "rowIndex": 1,
      "activityName": "",
      "eventTime": "10-01-2022 00:00",
      "eventDateTime": "2022-10-01 00:00",
      "location": "Saka Saka Limited Taiwan Branch",
      "address": "台北市中山區林森北路372號6樓之一",
      "rank": "-",
      "lp": "-"
    }
  ]
}
