{
  "id": "tw16802318",
  "url": "https://asia.pokemon-card.com/tw/users/tw16802318/?eventFilter=4&eventGivingCSPPointsFlg=1",
  "fetchedAt": "2026-04-19T03:24:49.841Z",
  "totalEvents": 1,
  "participatedTournaments": [
    {
      "pageNo": 1,
      "rowIndex": 1,
      "activityName": "2025-26 Taiwan Great Ball League Season 2",
      "eventTime": "11-22-2025 14:00",
      "eventDateTime": "2025-11-22 14:00",
      "location": "南瓜鎮",
      "address": "新北市三峽區國光街91號",
      "rank": "-",
      "lp": "-"
    }
  ]
}
