{
  "id": "tw22775249",
  "url": "https://asia.pokemon-card.com/tw/users/tw22775249/?eventFilter=4&eventGivingCSPPointsFlg=1",
  "fetchedAt": "2026-04-28T03:15:14.170Z",
  "totalEvents": 11,
  "participatedTournaments": [
    {
      "pageNo": 1,
      "rowIndex": 8,
      "activityName": "2025-26 Taiwan Master Ball League TCG Division Masters Category",
      "eventTime": "06-13-2026 08:00",
      "eventDateTime": "2026-06-13 08:00",
      "location": "The Pokémon Company",
      "address": "Roppongi Hills Mori Tower 8F, 6-10-1 Roppongi, Minato-ku, Tokyo, Japan",
      "rank": "-",
      "lp": "-"
    },
    {
      "pageNo": 1,
      "rowIndex": 11,
      "activityName": "2025-26 Taiwan Great Ball League Season 3",
      "eventTime": "04-19-2026 13:30",
      "eventDateTime": "2026-04-19 13:30",
      "location": "雙子星高雄鹽埕店",
      "address": "高雄市鹽埕區田單街17號",
      "rank": "-",
      "lp": "-"
    },
    {
      "pageNo": 1,
      "rowIndex": 10,
      "activityName": "2025-26 Taiwan Great Ball League Season 3",
      "eventTime": "04-18-2026 13:30",
      "eventDateTime": "2026-04-18 13:30",
      "location": "漢謚玩具社",
      "address": "高雄市苓雅區中華四路244號2樓",
      "rank": "49",
      "lp": "-"
    },
    {
      "pageNo": 1,
      "rowIndex": 9,
      "activityName": "2025-26 Taiwan Great Ball League Season 3",
      "eventTime": "04-05-2026 13:00",
      "eventDateTime": "2026-04-05 13:00",
      "location": "Bruce桌遊空間-三多店",
      "address": "高雄市前鎮區三多三路213號8樓",
      "rank": "-",
      "lp": "-"
    },
    {
      "pageNo": 1,
      "rowIndex": 7,
      "activityName": "2025-26 Taiwan Great Ball League Season 2",
      "eventTime": "01-03-2026 13:30",
      "eventDateTime": "2026-01-03 13:30",
      "location": "松梅桌遊",
      "address": "高雄市前鎮區瑞興街11號",
      "rank": "50",
      "lp": "-"
    },
    {
      "pageNo": 1,
      "rowIndex": 1,
      "activityName": "2025-26 Taiwan Premier Ball League TCG Division Masters Category",
      "eventTime": "11-01-2025 09:00",
      "eventDateTime": "2025-11-01 09:00",
      "location": "The Pokémon Company",
      "address": "Roppongi Hills Mori Tower 8F, 6-10-1 Roppongi, Minato-ku, Tokyo, Japan",
      "rank": "2200",
      "lp": "-"
    },
    {
      "pageNo": 1,
      "rowIndex": 6,
      "activityName": "2025-26 Taiwan Great Ball League Season 1",
      "eventTime": "09-28-2025 13:00",
      "eventDateTime": "2025-09-28 13:00",
      "location": "雙子星高雄鹽埕店",
      "address": "高雄市鹽埕區田單街17號",
      "rank": "26",
      "lp": "-"
    },
    {
      "pageNo": 1,
      "rowIndex": 4,
      "activityName": "2025-26 Taiwan Great Ball League Season 1",
      "eventTime": "09-28-2025 09:00",
      "eventDateTime": "2025-09-28 09:00",
      "location": "桌遊帝國咖啡廳",
      "address": "高雄市三民區建昌路35號",
      "rank": "-",
      "lp": "-"
    },
    {
      "pageNo": 1,
      "rowIndex": 5,
      "activityName": "2025-26 Taiwan Great Ball League Season 1",
      "eventTime": "09-27-2025 13:00",
      "eventDateTime": "2025-09-27 13:00",
      "location": "Bruce桌遊空間-嫩江店",
      "address": "高雄市三民區嫩江街74號2樓",
      "rank": "-",
      "lp": "-"
    },
    {
      "pageNo": 1,
      "rowIndex": 3,
      "activityName": "2025-26 Taiwan Great Ball League Season 1",
      "eventTime": "09-13-2025 13:30",
      "eventDateTime": "2025-09-13 13:30",
      "location": "漢謚玩具社",
      "address": "高雄市苓雅區中華四路244號2樓",
      "rank": "-",
      "lp": "-"
    },
    {
      "pageNo": 1,
      "rowIndex": 2,
      "activityName": "2025-26 Taiwan Great Ball League Season 1",
      "eventTime": "09-06-2025 13:30",
      "eventDateTime": "2025-09-06 13:30",
      "location": "松梅桌遊",
      "address": "高雄市前鎮區瑞興街11號",
      "rank": "37",
      "lp": "-"
    }
  ]
}
