{
  "id": "tw72889797",
  "url": "https://asia.pokemon-card.com/tw/users/tw72889797/?eventFilter=4&eventGivingCSPPointsFlg=1",
  "fetchedAt": "2026-05-02T22:36:57.218Z",
  "totalEvents": 1,
  "participatedTournaments": [
    {
      "pageNo": 1,
      "rowIndex": 1,
      "activityName": "2025-26 Taiwan Great Ball League Season 3",
      "eventTime": "03-29-2026 10:30",
      "eventDateTime": "2026-03-29 10:30",
      "location": "Card-Ple卡片人",
      "address": "新北市新莊區民安西路120號2樓",
      "rank": "28",
      "lp": "-"
    }
  ]
}
